{
    "$schema": "../schemas/pokedex.json",
    "name": "kanto",
    "pokemons": [
        {
            "number": 1,
            "name": "bulbasaur"
        },
        {
            "number": 2,
            "name": "ivysaur"
        },
        {
            "number": 11,
            "name": "metapod"
        },
        {
            "number": 43,
            "name": "oddish"
        },
        {
            "number": 47,
            "name": "parasect"
        },
        {
            "number": 55,
            "name": "golduck"
        },
        {
            "number": 57,
            "name": "primeape"
        },
        {
            "number": 61,
            "name": "poliwhirl"
        },
        {
            "number": 73,
            "name": "tentacruel"
        },
        {
            "number": 85,
            "name": "dodrio"
        },
        {
            "number": 86,
            "name": "seel"
        },
        {
            "number": 98,
            "name": "krabby"
        },
        {
            "number": 115,
            "name": "kangaskhan"
        },
        {
            "number": 121,
            "name": "starmie"
        },
        {
            "number": 131,
            "name": "lapras"
        },
        {
            "number": 134,
            "name": "vaporeon"
        },
        {
            "number": 135,
            "name": "jolteon"
        },
        {
            "number": 138,
            "name": "omanyte"
        },
        {
            "number": 146,
            "name": "moltres"
        }
    ]
}