{
    "$schema": "../schemas/pokedex.json",
    "name": "paldea",
    "gen": "9.0",
    "pokemons": {
        "lechonk": {
            "number": 915
        },
        "oinkologne": {
            "number": 916,
            "forms": {
                "hembra": {
                    "name": "Hembra",
                    "sprite": "https://raw.githubusercontent.com/PokeAPI/sprites/master/sprites/pokemon/10254.png"
                }
            }
        },
        "maushold": {
            "number": 925
        },
        "tinkaton": {
            "number": 959
        },
        "varoom": {
            "number": 965
        },
        "dudunsparce": {
            "number": 982
        },
        "iron-bundle": {
            "number": 991,
            "display": "ferrosaco"
        },
        "iron-thorns": {
            "number": 995,
            "display": "ferropúas"
        },
        "baxcalibur": {
            "number": 998,
            "forms": {
                "mega": {
                    "name": "Mega",
                    "sprite": "https://raw.githubusercontent.com/PokeAPI/sprites/master/sprites/pokemon/other/official-artwork/10325.png"
                }
            }
        },
        "chien-pao": {
            "number": 1002
        },
        "dipplin": {
            "number": 1011
        }
    }
}
